rabbithole/__init__.py
rabbithole/amqp.py
rabbithole/batcher.py
rabbithole/cli.py
rabbithole/sql.py
rabbithole-0.3.0.dist-info/DESCRIPTION.rst
rabbithole-0.3.0.dist-info/METADATA
rabbithole-0.3.0.dist-info/RECORD
rabbithole-0.3.0.dist-info/WHEEL
rabbithole-0.3.0.dist-info/entry_points.txt
rabbithole-0.3.0.dist-info/metadata.json
rabbithole-0.3.0.dist-info/top_level.txt
