Metadata-Version: 2.0
Name: rabbithole
Version: 0.3.0
Summary: Store messages from an AMQP server into a SQL database
Home-page: https://github.com/jcollado/rabbithole
Author: Javier Collado
Author-email: javier@gigaspaces.com
License: MIT license
Keywords: rabbithole
Platform: UNKNOWN
Classifier: Development Status :: 2 - Pre-Alpha
Classifier: Intended Audience :: Developers
Classifier: License :: OSI Approved :: MIT License
Classifier: Natural Language :: English
Classifier: Programming Language :: Python :: 2
Classifier: Programming Language :: Python :: 2.7
Classifier: Programming Language :: Python :: 3
Classifier: Programming Language :: Python :: 3.5
Requires-Dist: PyYAML
Requires-Dist: blinker
Requires-Dist: pika
Requires-Dist: sqlalchemy
Requires-Dist: typing
Provides-Extra: postgresql
Requires-Dist: psycopg2; extra == 'postgresql'
